DeltaTopic/__init__.py
DeltaTopic/datasets/__init__.py
DeltaTopic/datasets/_datasets.py
DeltaTopic/nn/TrainingPlan.py
DeltaTopic/nn/__init__.py
DeltaTopic/nn/base_components.py
DeltaTopic/nn/base_model.py
DeltaTopic/nn/dataloader_util.py
DeltaTopic/nn/modelhub.py
DeltaTopic/nn/module.py
DeltaTopic/nn/util.py
DeltaTopic/nn/util_benchmark.py
DeltaTopic/run/BALSAM.py
DeltaTopic/run/DeltaTopic.py
DeltaTopic/run/__init__.py
DeltaTopic-0.1.0.dist-info/LICENSE
DeltaTopic-0.1.0.dist-info/METADATA
DeltaTopic-0.1.0.dist-info/WHEEL
DeltaTopic-0.1.0.dist-info/entry_points.txt
DeltaTopic-0.1.0.dist-info/top_level.txt
DeltaTopic-0.1.0.dist-info/RECORD
