Metadata-Version: 2.1
Name: DeltaTopic
Version: 0.1.0
Summary: Packages to implement BALSAM and DeltaTopic as described in the paper: Unraveling dynamically-encoded latent transcriptomic patterns in pancreatic cancer cells by topic modelling
Home-page: https://github.com/causalpathlab/deltaTopic
Author: Yichen Zhang
License: UNKNOWN
Platform: UNKNOWN
License-File: LICENSE
Requires-Dist: pandas (==1.4.1)
Requires-Dist: torch (==2.0.0)
Requires-Dist: h5py (==3.6.0)
Requires-Dist: numpy (==1.21.0)
Requires-Dist: anndata (==0.7.8)
Requires-Dist: pytorch-lightning (==1.9.0)
Requires-Dist: scanpy (==1.9.3)
Requires-Dist: scipy (==1.8.0)
